{
	"name": "folha tela inicial",
	"events": [
		{
			"eventType": "block",
			"conditions": [
				{
					"id": "on-key-pressed",
					"objectClass": "Teclado",
					"sid": 157303284112527,
					"parameters": {
						"key": 13
					}
				}
			],
			"actions": [
				{
					"id": "go-to-layout",
					"objectClass": "System",
					"sid": 726152408662777,
					"parameters": {
						"layout": "Cenario1"
					}
				},
				{
					"id": "play",
					"objectClass": "Áudio",
					"sid": 426804495653692,
					"parameters": {
						"audio-file": "Click Start",
						"loop": "not-looping",
						"volume": "0",
						"stereo-pan": "0",
						"tag-optional": "\"\""
					}
				}
			],
			"sid": 465958172517266
		}
	],
	"sid": 775060274021940
}